LICENSE
MANIFEST.in
README.rst
setup.py
dj_mano/__init__.py
dj_mano/fields.py
dj_mano/utils.py
dj_mano.egg-info/PKG-INFO
dj_mano.egg-info/SOURCES.txt
dj_mano.egg-info/dependency_links.txt
dj_mano.egg-info/top_level.txt
dj_mano/management/__init__.py
dj_mano/management/commands/__init__.py
dj_mano/management/commands/dj_mano_sync.py