Metadata-Version: 1.1
Name: dj-mano
Version: 0.2.1
Summary: Materialized Annotations for Django Models
Home-page: https://github.com/ActivKonnect/dj_mano
Author: Rémy Sanchez
Author-email: remy.sanchez@activkonnect.com
License: UNKNOWN
Platform: UNKNOWN
Classifier: Environment :: Web Environment
Classifier: Framework :: Django
Classifier: Intended Audience :: Developers
Classifier: License :: Other/Proprietary License
Classifier: Operating System :: OS Independent
Classifier: Programming Language :: Python
Classifier: Programming Language :: Python :: 2
Classifier: Programming Language :: Python :: 3
Classifier: Topic :: Internet :: WWW/HTTP
Classifier: Topic :: Internet :: WWW/HTTP :: Dynamic Content
